poetry_pipx/__init__.py
poetry_pipx/py.typed
poetry_pipx-0.0.0.dist-info/LICENSE
poetry_pipx-0.0.0.dist-info/METADATA
poetry_pipx-0.0.0.dist-info/WHEEL
poetry_pipx-0.0.0.dist-info/RECORD
