Metadata-Version: 2.1
Name: poetry-pipx
Version: 0.0.0
Summary: A Poetry plugin that allows pipx to take precedence when installing CLI dependencies.
Home-page: https://github.com/bswck/poetry-pipx
License: MIT
Author: bswck
Author-email: bswck.dev@gmail.com
Requires-Python: >=3.8,<4.0
Classifier: License :: OSI Approved :: MIT License
Classifier: Programming Language :: Python :: 3
Classifier: Programming Language :: Python :: 3.8
Classifier: Programming Language :: Python :: 3.9
Classifier: Programming Language :: Python :: 3.10
Classifier: Programming Language :: Python :: 3.11
Classifier: Programming Language :: Python :: 3.12
Project-URL: Coverage, https://coverage-badge.samuelcolvin.workers.dev/redirect/bswck/poetry-pipx
Project-URL: Documentation, https://poetry-pipx.readthedocs.io/en/latest/
Project-URL: Distribution, https://pypi.org/project/poetry-pipx/
Project-URL: Issues, https://github.com/bswck/poetry-pipx/issues
